sapiensnb/__01010101.py
sapiensnb/__init__.py
sapiensnb/core.py
sapiensnb/sapiensnb.py
sapiensnb-1.0.4.dist-info/LICENSE.txt
sapiensnb-1.0.4.dist-info/METADATA
sapiensnb-1.0.4.dist-info/WHEEL
sapiensnb-1.0.4.dist-info/top_level.txt
sapiensnb-1.0.4.dist-info/RECORD
