Metadata-Version: 2.1
Name: sapiensnb
Version: 1.0.4
Summary: SapiensNB (Naive Bayes) is a classification algorithm that returns a probabilistic result based on Bayes Theorem.
Home-page: https://github.com/sapiens-technology/SapiensNB
Author: SAPIENS TECHNOLOGY
License: Proprietary Software
Project-URL: Source code, https://github.com/sapiens-technology/SapiensNB
Project-URL: Download, https://github.com/sapiens-technology/SapiensNB/archive/refs/heads/main.zip
Keywords: Sapiens,Artificial Intelligence,Machine Learning,Data Science,AI,ML,Naive Bayes
License-File: LICENSE.txt
